preadator/__init__.py
preadator/preadator.py
tests/__init__.py
tests/docker_test.py
tests/process_test.py
tests/thread_test.py
preadator-0.2.0.dist-info/LICENSE
preadator-0.2.0.dist-info/METADATA
preadator-0.2.0.dist-info/WHEEL
preadator-0.2.0.dist-info/top_level.txt
preadator-0.2.0.dist-info/RECORD
