Metadata-Version: 2.1
Name: preadator
Version: 0.2.0
Summary: Process and Thread Management Utility.
Home-page: https://github.com/LabShare/polus-plugins/tree/master/utils/polus-preadator-util/
Author: Nick Schaub
Author-email: nick.schaub@labshare.org
License: UNKNOWN
Platform: UNKNOWN
Classifier: Programming Language :: Python :: 3
Classifier: License :: OSI Approved :: MIT License
Classifier: Operating System :: OS Independent
Requires-Python: >=3.9
